iam_actions/__init__.py
iam_actions/actions.json
iam_actions/data.py
iam_actions/generate/__init__.py
iam_actions/generate/action_map.py
iam_actions/generate/aws_docs.py
iam_actions/generate/generate.py
iam_actions/generate/notifier.py
iam_actions/generate/resource_type.py
iam_actions/generate/services.py
iam_actions/policies.json
iam_actions/resourcetypes.json
iam_actions/services.json
iam_actions-1.2.99999999.dist-info/LICENSE
iam_actions-1.2.99999999.dist-info/WHEEL
iam_actions-1.2.99999999.dist-info/METADATA
iam_actions-1.2.99999999.dist-info/RECORD
