Metadata-Version: 2.1
Name: iam-actions
Version: 1.2.99999999
Summary: JSON of AWS policy components
Home-page: https://github.com/constableapp/iam_actions
License: MIT
Author: Constable
Author-email: info@constableapp.com
Requires-Python: >=3.9,<4.0
Classifier: License :: OSI Approved :: MIT License
Classifier: Programming Language :: Python :: 3
Classifier: Programming Language :: Python :: 3.9
Classifier: Programming Language :: Python :: 3.10
Classifier: Programming Language :: Python :: 3.11
Project-URL: Repository, https://github.com/constableapp/iam_actions
